flask_imp/__init__.py
flask_imp/__version__.py
flask_imp/_exceptions.py
flask_imp/_imp.py
flask_imp/_imp_blueprint.py
flask_imp/_protocols.py
flask_imp/_registries.py
flask_imp/_utilities.py
flask_imp/py.typed
flask_imp/utilities.py
flask_imp/_cli/__init__.py
flask_imp/_cli/blueprint.py
flask_imp/_cli/helpers.py
flask_imp/_cli/init.py
flask_imp/_cli/filelib/__init__.py
flask_imp/_cli/filelib/api_blueprint.py
flask_imp/_cli/filelib/blueprint.py
flask_imp/_cli/filelib/extensions.py
flask_imp/_cli/filelib/head_tag_generator.py
flask_imp/_cli/filelib/init.py
flask_imp/_cli/filelib/main_js.py
flask_imp/_cli/filelib/models.py
flask_imp/_cli/filelib/resources.py
flask_imp/_cli/filelib/templates.py
flask_imp/_cli/filelib/water_css.py
flask_imp/auth/__init__.py
flask_imp/auth/_authenticate_password.py
flask_imp/auth/_dataclasses.py
flask_imp/auth/_encrypt_password.py
flask_imp/auth/_generate_alphanumeric_validator.py
flask_imp/auth/_generate_csrf_token.py
flask_imp/auth/_generate_email_validator.py
flask_imp/auth/_generate_numeric_validator.py
flask_imp/auth/_generate_password.py
flask_imp/auth/_generate_private_key.py
flask_imp/auth/_generate_salt.py
flask_imp/auth/_is_email_address_valid.py
flask_imp/auth/_is_username_valid.py
flask_imp/auth/_private_funcs.py
flask_imp/config/__init__.py
flask_imp/config/_database_config.py
flask_imp/config/_flask_config.py
flask_imp/config/_imp_blueprint_config.py
flask_imp/config/_imp_config.py
flask_imp/config/_sql_database_config.py
flask_imp/config/_sqlite_database_config.py
flask_imp/security/__init__.py
flask_imp/security/_checkpoint.py
flask_imp/security/_checkpoint_callable.py
flask_imp/security/_checkpoints.py
flask_imp/security/_include_csrf.py
flask_imp-6.0.3.dist-info/entry_points.txt
flask_imp-6.0.3.dist-info/licenses/LICENSE.txt
flask_imp-6.0.3.dist-info/WHEEL
flask_imp-6.0.3.dist-info/METADATA
flask_imp-6.0.3.dist-info/RECORD
