Metadata-Version: 2.4
Name: flask-imp
Version: 6.0.3
Summary: A Flask auto importer that allows your Flask apps to grow big.
Author-email: David Carmichael <david@uilix.com>
Requires-Python: >=3.9
Classifier: Development Status :: 5 - Production/Stable
Classifier: License :: OSI Approved :: MIT License
Classifier: Framework :: Flask
Classifier: Natural Language :: English
License-File: LICENSE.txt
Requires-Dist: click
Requires-Dist: Flask
Requires-Dist: Flask-SQLAlchemy
Requires-Dist: more-itertools
Project-URL: Documentation, https://cheesecake87.github.io/flask-imp/
Project-URL: Source, https://github.com/CheeseCake87/flask-imp
